<?xml version="1.0" encoding="utf-8" ?>
<dwsync>
<file name="App.config" server="C:/xampp/htdocs/proman/" local="131688977115290783" remote="131688977110000000" Dst="2" />
<file name="packages.config" server="C:/xampp/htdocs/proman/" local="131688977116331480" remote="131688977110000000" Dst="2" />
<file name="ProMan_BusinessLayer.csproj" server="C:/xampp/htdocs/proman/" local="131688977116281435" remote="131688977110000000" Dst="2" />
<file name="App.config" server="192.168.178.26" local="131688977115290783" remote="131688979800000000" Dst="2" />
<file name="packages.config" server="192.168.178.26" local="131688977116331480" remote="131688979800000000" Dst="2" />
<file name="ProMan_BusinessLayer.csproj" server="192.168.178.26" local="131688977116281435" remote="131688979800000000" Dst="2" />
<file name="KeyValueHelper.cs" server="C:/xampp/htdocs/proman/" local="131688977115661024" remote="131688977110000000" Dst="2" />
<file name="KeyValueHelper.cs" server="192.168.178.26" local="131688977115661024" remote="131688979800000000" Dst="2" />
</dwsync>